Metadata-Version: 2.4
Name: x402-client
Version: 0.1.0
Summary: Python client for the x402 Payment Protocol (v2) - HTTP 402 payments made easy
Project-URL: Homepage, https://github.com/agentokratia/x402-client
Project-URL: Documentation, https://github.com/agentokratia/x402-client#readme
Project-URL: Repository, https://github.com/agentokratia/x402-client
Project-URL: Issues, https://github.com/agentokratia/x402-client/issues
Project-URL: Changelog, https://github.com/agentokratia/x402-client/blob/main/CHANGELOG.md
Author-email: Agentokratia <dev@agentokratia.com>
License-Expression: MIT
License-File: LICENSE
Keywords: blockchain,eip-3009,ethereum,http-402,micropayments,payments,usdc,web3,x402
Classifier: Development Status :: 4 - Beta
Classifier: Intended Audience :: Developers
Classifier: License :: OSI Approved :: MIT License
Classifier: Operating System :: OS Independent
Classifier: Programming Language :: Python :: 3
Classifier: Programming Language :: Python :: 3.10
Classifier: Programming Language :: Python :: 3.11
Classifier: Programming Language :: Python :: 3.12
Classifier: Programming Language :: Python :: 3.13
Classifier: Topic :: Internet :: WWW/HTTP
Classifier: Topic :: Software Development :: Libraries :: Python Modules
Classifier: Typing :: Typed
Requires-Python: >=3.10
Requires-Dist: eth-account>=0.11.0
Requires-Dist: httpx>=0.27.0
Provides-Extra: dev
Requires-Dist: mypy>=1.0.0; extra == 'dev'
Requires-Dist: pytest-asyncio>=0.23.0; extra == 'dev'
Requires-Dist: pytest>=8.0.0; extra == 'dev'
Requires-Dist: ruff>=0.1.0; extra == 'dev'
